mag2exp/__init__.py
mag2exp/fmr.py
mag2exp/ltem.py
mag2exp/magnetometry.py
mag2exp/mfm.py
mag2exp/moke.py
mag2exp/quick_plots.py
mag2exp/sans.py
mag2exp/x_ray.py
mag2exp/tests/__init__.py
mag2exp/tests/test_fmr.py
mag2exp/tests/test_ltem.py
mag2exp/tests/test_magnetisation.py
mag2exp/tests/test_mfm.py
mag2exp/tests/test_moke.py
mag2exp/tests/test_quick_plots.py
mag2exp/tests/test_sans.py
mag2exp/tests/test_util.py
mag2exp/tests/test_x_ray.py
mag2exp/util/__init__.py
mag2exp/util/util.py
mag2exp-0.64.0.dist-info/licenses/LICENSE
mag2exp-0.64.0.dist-info/METADATA
mag2exp-0.64.0.dist-info/WHEEL
mag2exp-0.64.0.dist-info/top_level.txt
mag2exp-0.64.0.dist-info/RECORD
