Metadata-Version: 2.4
Name: mag2exp
Version: 0.64.0
Summary: Simulate experimental measurements for magnetic materials
Author: Samuel Holt, Martin Lang, James Loudon, Thomas Hicken, Swapneel Amit Pathak, David Cortés Ortuño, Marijan Beg, Hans Fangohr
License-Expression: BSD-3-Clause
Project-URL: homepage, https://ubermag.github.io
Project-URL: documentation, https://ubermag.github.io/documentation/mag2exp
Project-URL: repository, https://github.com/ubermag/mag2exp
Classifier: Development Status :: 5 - Production/Stable
Classifier: Intended Audience :: Education
Classifier: Intended Audience :: Developers
Classifier: Intended Audience :: Science/Research
Classifier: Natural Language :: English
Classifier: Operating System :: MacOS
Classifier: Operating System :: Microsoft :: Windows
Classifier: Operating System :: Unix
Classifier: Programming Language :: Python :: 3 :: Only
Classifier: Topic :: Scientific/Engineering :: Physics
Classifier: Topic :: Scientific/Engineering :: Mathematics
Classifier: Topic :: Scientific/Engineering :: Visualization
Requires-Python: >=3.9
License-File: LICENSE
Requires-Dist: oommfc>=0.66.0
Requires-Dist: numpy>=1.19
Requires-Dist: scipy>=1.6
Provides-Extra: dev
Requires-Dist: build; extra == "dev"
Requires-Dist: invoke; extra == "dev"
Requires-Dist: nbval; extra == "dev"
Requires-Dist: pre-commit; extra == "dev"
Requires-Dist: pytest-cov; extra == "dev"
Requires-Dist: twine; extra == "dev"
Requires-Dist: tomli; python_version < "3.11" and extra == "dev"
Dynamic: license-file
